my_similarity_package/__init__.py
my_similarity_package/similarity.py
tests/__init__.py
tests/test_CosineSimilarity.py
my_similarity_package-0.1.dist-info/METADATA
my_similarity_package-0.1.dist-info/WHEEL
my_similarity_package-0.1.dist-info/top_level.txt
my_similarity_package-0.1.dist-info/RECORD
