Metadata-Version: 2.1
Name: my_similarity_package
Version: 0.1
Summary: A package for calculating cosine similarity between sentences
Author: Your Name
Author-email: your.email@example.com
License: MIT
Requires-Dist: pandas
Requires-Dist: numpy
Requires-Dist: nltk
